apirun/HTMLTestRunner_Modified.py
apirun/PressureTest.py
apirun/PtSlave.py
apirun/__init__.py
apirun/dealParameter.py
apirun/extractExcel.py
apirun/genReport.py
apirun/getToken.py
apirun/mail.py
apirun/main.py
apirun/demo/demo_pressuretest.xls
apirun/demo/demo_testcase.xls
apirun/demo/email.json
apirun/js/echarts.common.min.js
apirun-0.2.12.data/data/README.md
apirun-0.2.12.dist-info/LICENSE
apirun-0.2.12.dist-info/METADATA
apirun-0.2.12.dist-info/WHEEL
apirun-0.2.12.dist-info/entry_points.txt
apirun-0.2.12.dist-info/top_level.txt
apirun-0.2.12.dist-info/RECORD
